{
  "consumeCatalyst": false,
  "location": "teststar:simple_washing_machine",
  "traits": {
    "background": "multiblocked:textures/gui/simple_washing_machine.png",
    "item": [
      {
        "cIO": 0,
        "gIO": 2,
        "x": 24,
        "y": 66,
        "autoIO": false
      },
      {
        "cIO": 1,
        "gIO": 1,
        "x": 115,
        "y": 48,
        "autoIO": false
      },
      {
        "cIO": 1,
        "gIO": 1,
        "x": 133,
        "y": 48,
        "autoIO": false
      },
      {
        "cIO": 1,
        "gIO": 1,
        "x": 151,
        "y": 48,
        "autoIO": false
      },
      {
        "cIO": 1,
        "gIO": 1,
        "x": 115,
        "y": 66,
        "autoIO": false
      },
      {
        "cIO": 1,
        "gIO": 1,
        "x": 133,
        "y": 66,
        "autoIO": false
      },
      {
        "cIO": 1,
        "gIO": 1,
        "x": 151,
        "y": 66,
        "autoIO": false
      },
      {
        "cIO": 1,
        "gIO": 1,
        "x": 115,
        "y": 84,
        "autoIO": false
      },
      {
        "cIO": 1,
        "gIO": 1,
        "x": 133,
        "y": 84,
        "autoIO": false
      },
      {
        "cIO": 1,
        "gIO": 1,
        "x": 151,
        "y": 84,
        "autoIO": false
      }
    ],
    "fluid": [
      {
        "cIO": 0,
        "gIO": 0,
        "x": 6,
        "y": 66,
        "autoIO": false,
        "tC": 6000
      }
    ]
  },
  "allowRotate": true,
  "showInJei": true,
  "baseRenderer": {
    "state": {
      "id": "kubejs:purpur_dust_block",
      "meta": 0
    },
    "type": "blockstate"
  },
  "formedRenderer": {
    "state": {
      "id": "minecraft:furnace",
      "meta": 1
    },
    "type": "blockstate"
  },
  "workingRenderer": {
    "state": {
      "id": "minecraft:furnace",
      "meta": 0
    },
    "type": "blockstate"
  },
  "properties": {
    "isOpaque": true,
    "destroyTime": 1.5,
    "explosionResistance": 6.0,
    "lightEmissive": 0,
    "speedFactor": 1.0,
    "jumpFactor": 1.0,
    "friction": 0.6,
    "hasCollision": true,
    "tabGroup": "multiblocked.all",
    "stackSize": 64
  },
  "basePattern": {
    "structureDir": [
      "BACK",
      "UP",
      "RIGHT"
    ],
    "pattern": [
      [
        "ABA",
        "ABA",
        "ABA"
      ],
      [
        "BBB",
        "@ B",
        "BBB"
      ],
      [
        "ABA",
        "ABA",
        "ABA"
      ]
    ],
    "aisleRepetitions": [
      [
        1,
        1
      ],
      [
        1,
        1
      ],
      [
        1,
        1
      ]
    ],
    "predicates": {
      "A": {
        "blocks": [
          {
            "id": "minecraft:purpur_block"
          }
        ],
        "type": "blocks"
      },
      "controller": {
        "location": "teststar:simple_washing_machine",
        "type": "component"
      },
      "B": {
        "blocks": [
          {
            "id": "kubejs:purpur_dust_block"
          }
        ],
        "type": "blocks"
      },
      "any": {
        "type": "any"
      }
    },
    "symbolMap": {
      "@": [
        "controller"
      ],
      " ": [
        "any"
      ],
      "A": [
        "A"
      ],
      "B": [
        "B"
      ]
    }
  },
  "recipeMap": "swm_recipes"
}